bitefix/BiteFixAIAgents.py
bitefix/BiteFixAICrew.py
bitefix/BiteFixAIRunner.py
bitefix/BiteFixAITasks.py
bitefix/__init__.py
bitefix/bitefix_utils.py
bitefix-1.0.2.dist-info/LICENSE
bitefix-1.0.2.dist-info/METADATA
bitefix-1.0.2.dist-info/WHEEL
bitefix-1.0.2.dist-info/top_level.txt
bitefix-1.0.2.dist-info/RECORD
