Metadata-Version: 2.1
Name: bitefix
Version: 1.0.2
Summary: Bitefix is an efficient library designed to streamline Python Runtime error debugging with AI-powered decorators. 
Home-page: https://github.com/Pallavi-Sinha-12/bitefix
Author: Pallavi Sinha
Author-email: dataaienthusiast128@gmail.com
License: MIT
Classifier: Programming Language :: Python :: 3
Classifier: License :: OSI Approved :: MIT License
Classifier: Operating System :: OS Independent
Requires-Python: >=3.10
License-File: LICENSE
Requires-Dist: crewai ==0.14.4
Requires-Dist: langchain ==0.1.9
Requires-Dist: crewai-tools ==0.0.12
